{"owNIScdKSsYOyZct3F5jhw==":"dsc-572.jpg","/Fc2E/JdXrEnAQLZctim5A==":"allover-geel-op-rood.jpg","nvGqU/DB+CYS4X9DjZv41g==":"zwart-wit-zwart.jpg","UAc7kepzJPkrSn4uqTRvmw==":"background4.jpg","XVDOLRn+19cxNAbWgofv5g==":"20160104-4011601.jpg","Dc9TDDJTtrIN58QwwJi7JQ==":"20160104-4011602.jpg","SA4y1qSIcnCxhvQbbDtBqA==":"20160104-4011603.jpg","/0WyykcX7X1LTQJCHFZJmA==":"20160104-4011604.jpg","97mYzArzkK2A7yTpAVbnGQ==":"20160104-4011606.jpg","YZm470rVJT+dTLvR7kagKQ==":"20160104-4011617.jpg","FQUQ/9pLcpy5mG4EwnswlA==":"20160104-4011618.jpg","66YPpilm9yLa1I7uQOagyQ==":"20160104-4011605.jpg","FSjCXGd7ZfLQwEvi7sJ0UA==":"20160104-4011613.jpg","I7dTylYNdoWq7gEZMil1BQ==":"20160104-4011610.jpg","O/fstWhHljZ9F+YGJ7qOtA==":"20160104-4011611.jpg","thb5gQn5BmEfMThIC6OAUg==":"20160104-4011609.jpg","HCSDptVkc41bMo64Yk+cYw==":"20160104-4011608.jpg","DxgjM//jQg85PNfp8kqqVA==":"20160104-4011607.jpg","OBbxWq0dKl146Nqw/ATZJw==":"20160104-4011612.jpg","ChWkiHH/GIwQuSfy6CMqCQ==":"20160104-4011614.jpg"}